<?xml version="1.0" encoding="UTF-8"?><record_update>
    <sys_dictionary action="DELETE" element="x_58872_needit_u_campo_exercicio" table="incident">
        <active>true</active>
        <array>false</array>
        <array_denormalized>false</array_denormalized>
        <attributes>edge_encryption_enabled=true</attributes>
        <audit>false</audit>
        <calculation/>
        <choice>0</choice>
        <choice_field/>
        <choice_table/>
        <column_label>Campo editável somente com a role padawan</column_label>
        <comments/>
        <create_roles/>
        <default_value/>
        <defaultsort/>
        <delete_roles/>
        <dependent/>
        <dependent_on_field/>
        <display>false</display>
        <dynamic_creation>false</dynamic_creation>
        <dynamic_creation_script/>
        <dynamic_default_value/>
        <dynamic_ref_qual/>
        <element>x_58872_needit_u_campo_exercicio</element>
        <element_reference>false</element_reference>
        <foreign_database/>
        <function_definition/>
        <function_field>false</function_field>
        <internal_type display_value="String">string</internal_type>
        <mandatory>false</mandatory>
        <max_length>40</max_length>
        <name>incident</name>
        <next_element/>
        <primary>false</primary>
        <read_only>false</read_only>
        <read_roles/>
        <reference/>
        <reference_cascade_rule/>
        <reference_floats>false</reference_floats>
        <reference_key/>
        <reference_qual/>
        <reference_qual_condition/>
        <reference_type/>
        <sizeclass/>
        <spell_check>false</spell_check>
        <staged>false</staged>
        <sys_class_name>sys_dictionary</sys_class_name>
        <sys_created_by>admin</sys_created_by>
        <sys_created_on>2020-06-08 18:23:41</sys_created_on>
        <sys_id>e5339691db5950106a52e4da4b9619d4</sys_id>
        <sys_mod_count>1</sys_mod_count>
        <sys_name>Campo editável somente com a role padawan</sys_name>
        <sys_package display_value="NeedIt" source="x_58872_needit">6ead8e780f603200cd674f8ce1050ed1</sys_package>
        <sys_policy/>
        <sys_scope display_value="NeedIt">6ead8e780f603200cd674f8ce1050ed1</sys_scope>
        <sys_update_name>sys_dictionary_incident_x_58872_needit_u_campo_exercicio</sys_update_name>
        <sys_updated_by>admin</sys_updated_by>
        <sys_updated_on>2020-06-08 18:38:01</sys_updated_on>
        <table_reference>false</table_reference>
        <text_index>false</text_index>
        <unique>false</unique>
        <use_dependent_field>false</use_dependent_field>
        <use_dynamic_default>false</use_dynamic_default>
        <use_reference_qualifier>simple</use_reference_qualifier>
        <virtual>false</virtual>
        <widget/>
        <write_roles/>
        <xml_view>false</xml_view>
    </sys_dictionary>
    <sys_update_version action="INSERT_OR_UPDATE">
        <action>DELETE</action>
        <application display_value="NeedIt">6ead8e780f603200cd674f8ce1050ed1</application>
        <file_path/>
        <instance_id>51fd1532db64370052cec59705961979</instance_id>
        <instance_name>dev78919</instance_name>
        <name>sys_dictionary_incident_x_58872_needit_u_campo_exercicio</name>
        <payload><![CDATA[<?xml version="1.0" encoding="UTF-8"?><record_update><sys_dictionary action="INSERT_OR_UPDATE" element="x_58872_needit_u_campo_exercicio" table="incident"><active>true</active><array>false</array><array_denormalized>false</array_denormalized><attributes>edge_encryption_enabled=true</attributes><audit>false</audit><calculation/><choice>0</choice><choice_field/><choice_table/><column_label>Campo editável somente com a role padawan</column_label><comments/><create_roles/><default_value/><defaultsort/><delete_roles/><dependent/><dependent_on_field/><display>false</display><dynamic_creation>false</dynamic_creation><dynamic_creation_script/><dynamic_default_value/><dynamic_ref_qual/><element>x_58872_needit_u_campo_exercicio</element><element_reference>false</element_reference><foreign_database/><function_definition/><function_field>false</function_field><internal_type display_value="String">string</internal_type><mandatory>false</mandatory><max_length>40</max_length><name>incident</name><next_element/><primary>false</primary><read_only>false</read_only><read_roles/><reference/><reference_cascade_rule/><reference_floats>false</reference_floats><reference_key/><reference_qual/><reference_qual_condition/><reference_type/><sizeclass/><spell_check>false</spell_check><staged>false</staged><sys_class_name>sys_dictionary</sys_class_name><sys_created_by>admin</sys_created_by><sys_created_on>2020-06-08 18:23:41</sys_created_on><sys_id>e5339691db5950106a52e4da4b9619d4</sys_id><sys_mod_count>1</sys_mod_count><sys_name>Campo editável somente com a role padawan</sys_name><sys_package display_value="NeedIt" source="x_58872_needit">6ead8e780f603200cd674f8ce1050ed1</sys_package><sys_policy/><sys_scope display_value="NeedIt">6ead8e780f603200cd674f8ce1050ed1</sys_scope><sys_update_name>sys_dictionary_incident_x_58872_needit_u_campo_exercicio</sys_update_name><sys_updated_by>admin</sys_updated_by><sys_updated_on>2020-06-08 18:38:01</sys_updated_on><table_reference>false</table_reference><text_index>false</text_index><unique>false</unique><use_dependent_field>false</use_dependent_field><use_dynamic_default>false</use_dynamic_default><use_reference_qualifier>simple</use_reference_qualifier><virtual>false</virtual><widget/><write_roles/><xml_view>false</xml_view></sys_dictionary></record_update>]]></payload>
        <payload_hash>-227846517</payload_hash>
        <record_name>Incident.Campo editável somente com a role padawan</record_name>
        <reverted_from/>
        <source>5b92e47cdbc110106a52e4da4b9619ac</source>
        <source_table>sys_update_set</source_table>
        <state>previous</state>
        <sys_created_by>admin</sys_created_by>
        <sys_created_on>2020-06-08 18:38:01</sys_created_on>
        <sys_id>6b7656dddb9950106a52e4da4b961925</sys_id>
        <sys_mod_count>0</sys_mod_count>
        <sys_recorded_at>1729539a1e10000001</sys_recorded_at>
        <sys_updated_by>admin</sys_updated_by>
        <sys_updated_on>2020-06-08 18:38:01</sys_updated_on>
        <type>Dictionary</type>
        <update_guid>e37656dd6f9950107d7b3aa412b92f25</update_guid>
        <update_guid_history>e37656dd6f9950107d7b3aa412b92f25:-227846517,2933d6918b5950108ffdf490d030f99b:1095127415</update_guid_history>
    </sys_update_version>
    <sys_metadata_delete action="INSERT_OR_UPDATE">
        <sys_audit_delete/>
        <sys_class_name>sys_metadata_delete</sys_class_name>
        <sys_created_by>admin</sys_created_by>
        <sys_created_on>2020-06-08 18:53:23</sys_created_on>
        <sys_db_object display_value="" name="sys_dictionary">sys_dictionary</sys_db_object>
        <sys_id>0010d13f516543b2800007d77c10f944</sys_id>
        <sys_metadata>e5339691db5950106a52e4da4b9619d4</sys_metadata>
        <sys_mod_count>0</sys_mod_count>
        <sys_name>Campo editável somente com a role padawan</sys_name>
        <sys_package display_value="NeedIt" source="x_58872_needit">6ead8e780f603200cd674f8ce1050ed1</sys_package>
        <sys_parent display_value="Incident">ae32ecb8dbc110106a52e4da4b961944</sys_parent>
        <sys_policy/>
        <sys_scope display_value="NeedIt">6ead8e780f603200cd674f8ce1050ed1</sys_scope>
        <sys_scope_delete display_value="">94872a8897db403e8ee69a431de2fca4</sys_scope_delete>
        <sys_update_name>sys_dictionary_incident_x_58872_needit_u_campo_exercicio</sys_update_name>
        <sys_update_version display_value="sys_dictionary_incident_x_58872_needit_u_campo_exercicio">6b7656dddb9950106a52e4da4b961925</sys_update_version>
        <sys_updated_by>admin</sys_updated_by>
        <sys_updated_on>2020-06-08 18:53:23</sys_updated_on>
    </sys_metadata_delete>
</record_update>
